mgsub/__init__.py
mgsub/mgsub.py
mgsub/version.py
mgsub-0.1.0.dist-info/LICENSE
mgsub-0.1.0.dist-info/METADATA
mgsub-0.1.0.dist-info/WHEEL
mgsub-0.1.0.dist-info/top_level.txt
mgsub-0.1.0.dist-info/RECORD
