Metadata-Version: 2.1
Name: mgsub
Version: 0.1.0
Summary: A safe, multiple, simultaneous string substitution function
Home-page: https://github.com/bmewing/mgsub-python
Author: Mark Ewing
Author-email: b.mark@ewingsonline.com
License: UNKNOWN
Keywords: string,substitution,regex,regular expression
Platform: UNKNOWN
Classifier: Programming Language :: Python :: 3
Classifier: License :: OSI Approved :: MIT License
Classifier: Operating System :: OS Independent
